torchwindow/__init__.py
torchwindow/example.py
torchwindow/exceptions.py
torchwindow/shaders.py
torchwindow/window.py
torchwindow-1.1.0.dist-info/WHEEL
torchwindow-1.1.0.dist-info/METADATA
torchwindow-1.1.0.dist-info/RECORD
