Metadata-Version: 2.1
Name: torchwindow
Version: 1.1.0
Summary: Display tensors directly from GPU
Home-page: https://github.com/jbaron34/torchwindow
License: MIT
Author: Jeremy
Author-email: jbaron34@gmail.com
Requires-Python: >=3.8,<4.0
Classifier: License :: OSI Approved :: MIT License
Classifier: Programming Language :: Python :: 3
Classifier: Programming Language :: Python :: 3.8
Classifier: Programming Language :: Python :: 3.9
Classifier: Programming Language :: Python :: 3.10
Classifier: Programming Language :: Python :: 3.11
Requires-Dist: cuda-python (>=11.8.0,<12.0.0)
Requires-Dist: numpy (>=1.23.4,<2.0.0)
Requires-Dist: pyopengl (>=3.1.6,<4.0.0)
Requires-Dist: pysdl2 (>=0.9.14,<0.10.0)
Requires-Dist: pysdl2-dll (>=2.24.1,<3.0.0)
Project-URL: Repository, https://github.com/jbaron34/torchwindow
